[
{  "Rank" : "1", "Place" : "Yemen", "Continent" : "Asia", "Deaths to Cases - Last" : "0.2657" },
{  "Rank" : "", "Place" : "", "Continent" : "", "Deaths to Cases - Last" : "" },
{  "Rank" : "2", "Place" : "Sint Maarten", "Continent" : "North America", "Deaths to Cases - Last" : "0.1948" },
{  "Rank" : "", "Place" : "", "Continent" : "", "Deaths to Cases - Last" : "" },
{  "Rank" : "3", "Place" : "France", "Continent" : "Europe", "Deaths to Cases - Last" : "0.191" },
{  "Rank" : "", "Place" : "", "Continent" : "", "Deaths to Cases - Last" : "" },
{  "Rank" : "4", "Place" : "Belgium", "Continent" : "Europe", "Deaths to Cases - Last" : "0.1601" },
{  "Rank" : "", "Place" : "", "Continent" : "", "Deaths to Cases - Last" : "" },
{  "Rank" : "5", "Place" : "Italy", "Continent" : "Europe", "Deaths to Cases - Last" : "0.1452" },
{  "Rank" : "", "Place" : "", "Continent" : "", "Deaths to Cases - Last" : "" },
{  "Rank" : "6", "Place" : "The United Kingdom", "Continent" : "Europe", "Deaths to Cases - Last" : "0.1397" },
{  "Rank" : "", "Place" : "", "Continent" : "", "Deaths to Cases - Last" : "" },
{  "Rank" : "7", "Place" : "Hungary", "Continent" : "Europe", "Deaths to Cases - Last" : "0.1395" },
{  "Rank" : "", "Place" : "", "Continent" : "", "Deaths to Cases - Last" : "" },
{  "Rank" : "8", "Place" : "British Virgin Islands", "Continent" : "North America", "Deaths to Cases - Last" : "0.125" },
{  "Rank" : "", "Place" : "", "Continent" : "", "Deaths to Cases - Last" : "" },
{  "Rank" : "9", "Place" : "Netherlands", "Continent" : "Europe", "Deaths to Cases - Last" : "0.1226" },
{  "Rank" : "", "Place" : "", "Continent" : "", "Deaths to Cases - Last" : "" },
{  "Rank" : "10", "Place" : "Mexico", "Continent" : "North America", "Deaths to Cases - Last" : "0.1209" },
{  "Rank" : "", "Place" : "", "Continent" : "", "Deaths to Cases - Last" : "" },
{  "Rank" : "11", "Place" : "Antigua and Barbuda", "Continent" : "North America", "Deaths to Cases - Last" : "0.1154" },
{  "Rank" : "", "Place" : "", "Continent" : "", "Deaths to Cases - Last" : "" },
{  "Rank" : "12", "Place" : "Spain", "Continent" : "Europe", "Deaths to Cases - Last" : "0.1149" },
{  "Rank" : "", "Place" : "", "Continent" : "", "Deaths to Cases - Last" : "" },
{  "Rank" : "13", "Place" : "Bahamas", "Continent" : "North America", "Deaths to Cases - Last" : "0.1058" },
{  "Rank" : "", "Place" : "", "Continent" : "", "Deaths to Cases - Last" : "" },
{  "Rank" : "14", "Place" : "Jersey", "Continent" : "Europe", "Deaths to Cases - Last" : "0.0975" },
{  "Rank" : "", "Place" : "", "Continent" : "", "Deaths to Cases - Last" : "" },
{  "Rank" : "15", "Place" : "Belize", "Continent" : "North America", "Deaths to Cases - Last" : "0.0909" },
{  "Rank" : "", "Place" : "", "Continent" : "", "Deaths to Cases - Last" : "" },
{  "Rank" : "15", "Place" : "Montserrat", "Continent" : "North America", "Deaths to Cases - Last" : "0.0909" },
{  "Rank" : "", "Place" : "", "Continent" : "", "Deaths to Cases - Last" : "" },
{  "Rank" : "17", "Place" : "Sweden", "Continent" : "Europe", "Deaths to Cases - Last" : "0.0869" },
{  "Rank" : "", "Place" : "", "Continent" : "", "Deaths to Cases - Last" : "" },
{  "Rank" : "18", "Place" : "Chad", "Continent" : "Africa", "Deaths to Cases - Last" : "0.0862" },
{  "Rank" : "", "Place" : "", "Continent" : "", "Deaths to Cases - Last" : "" },
{  "Rank" : "19", "Place" : "Ecuador", "Continent" : "South America", "Deaths to Cases - Last" : "0.0834" },
{  "Rank" : "", "Place" : "", "Continent" : "", "Deaths to Cases - Last" : "" },
{  "Rank" : "20", "Place" : "Canada", "Continent" : "North America", "Deaths to Cases - Last" : "0.0832" },
{  "Rank" : "", "Place" : "", "Continent" : "", "Deaths to Cases - Last" : "" },
{  "Rank" : "21", "Place" : "Guadeloupe", "Continent" : "North America", "Deaths to Cases - Last" : "0.0805" },
{  "Rank" : "", "Place" : "", "Continent" : "", "Deaths to Cases - Last" : "" },
{  "Rank" : "22", "Place" : "United States Virgin Islands", "Continent" : "North America", "Deaths to Cases - Last" : "0.0789" },
{  "Rank" : "", "Place" : "", "Continent" : "", "Deaths to Cases - Last" : "" },
{  "Rank" : "23", "Place" : "Barbados", "Continent" : "North America", "Deaths to Cases - Last" : "0.0722" },
{  "Rank" : "", "Place" : "", "Continent" : "", "Deaths to Cases - Last" : "" },
{  "Rank" : "24", "Place" : "Slovenia", "Continent" : "Europe", "Deaths to Cases - Last" : "0.0717" },
{  "Rank" : "", "Place" : "", "Continent" : "", "Deaths to Cases - Last" : "" },
{  "Rank" : "25", "Place" : "Algeria", "Continent" : "Africa", "Deaths to Cases - Last" : "0.0715" },
{  "Rank" : "", "Place" : "", "Continent" : "", "Deaths to Cases - Last" : "" },
{  "Rank" : "26", "Place" : "Saint Martin", "Continent" : "North America", "Deaths to Cases - Last" : "0.0714" },
{  "Rank" : "", "Place" : "", "Continent" : "", "Deaths to Cases - Last" : "" },
{  "Rank" : "26", "Place" : "Turks and Caicos Islands", "Continent" : "North America", "Deaths to Cases - Last" : "0.0714" },
{  "Rank" : "", "Place" : "", "Continent" : "", "Deaths to Cases - Last" : "" },
{  "Rank" : "26", "Place" : "Isle of Man", "Continent" : "Europe", "Deaths to Cases - Last" : "0.0714" },
{  "Rank" : "", "Place" : "", "Continent" : "", "Deaths to Cases - Last" : "" },
{  "Rank" : "29", "Place" : "Ireland", "Continent" : "Europe", "Deaths to Cases - Last" : "0.0676" },
{  "Rank" : "", "Place" : "", "Continent" : "", "Deaths to Cases - Last" : "" },
{  "Rank" : "30", "Place" : "Northern Mariana Islands", "Continent" : "Oceania", "Deaths to Cases - Last" : "0.0667" },
{  "Rank" : "", "Place" : "", "Continent" : "", "Deaths to Cases - Last" : "" },
{  "Rank" : "31", "Place" : "Guyana", "Continent" : "South America", "Deaths to Cases - Last" : "0.0652" },
{  "Rank" : "", "Place" : "", "Continent" : "", "Deaths to Cases - Last" : "" },
{  "Rank" : "32", "Place" : "Trinidad and Tobago", "Continent" : "North America", "Deaths to Cases - Last" : "0.065" },
{  "Rank" : "", "Place" : "", "Continent" : "", "Deaths to Cases - Last" : "" },
{  "Rank" : "33", "Place" : "Niger", "Continent" : "Africa", "Deaths to Cases - Last" : "0.0641" },
{  "Rank" : "", "Place" : "", "Continent" : "", "Deaths to Cases - Last" : "" },
{  "Rank" : "34", "Place" : "Romania", "Continent" : "Europe", "Deaths to Cases - Last" : "0.0627" },
{  "Rank" : "", "Place" : "", "Continent" : "", "Deaths to Cases - Last" : "" },
{  "Rank" : "35", "Place" : "Bermuda", "Continent" : "North America", "Deaths to Cases - Last" : "0.0616" },
{  "Rank" : "", "Place" : "", "Continent" : "", "Deaths to Cases - Last" : "" },
{  "Rank" : "36", "Place" : "Sudan", "Continent" : "Africa", "Deaths to Cases - Last" : "0.0613" },
{  "Rank" : "", "Place" : "", "Continent" : "", "Deaths to Cases - Last" : "" },
{  "Rank" : "37", "Place" : "Andorra", "Continent" : "Europe", "Deaths to Cases - Last" : "0.0608" },
{  "Rank" : "", "Place" : "", "Continent" : "", "Deaths to Cases - Last" : "" },
{  "Rank" : "38", "Place" : "Martinique", "Continent" : "North America", "Deaths to Cases - Last" : "0.0593" },
{  "Rank" : "", "Place" : "", "Continent" : "", "Deaths to Cases - Last" : "" },
{  "Rank" : "39", "Place" : "San Marino", "Continent" : "Europe", "Deaths to Cases - Last" : "0.0589" },
{  "Rank" : "", "Place" : "", "Continent" : "", "Deaths to Cases - Last" : "" },
{  "Rank" : "40", "Place" : "Burkina Faso", "Continent" : "Africa", "Deaths to Cases - Last" : "0.0587" },
{  "Rank" : "", "Place" : "", "Continent" : "", "Deaths to Cases - Last" : "" },
{  "Rank" : "41", "Place" : "Greece", "Continent" : "Europe", "Deaths to Cases - Last" : "0.0578" },
{  "Rank" : "", "Place" : "", "Continent" : "", "Deaths to Cases - Last" : "" },
{  "Rank" : "42", "Place" : "Mali", "Continent" : "Africa", "Deaths to Cases - Last" : "0.0566" },
{  "Rank" : "", "Place" : "", "Continent" : "", "Deaths to Cases - Last" : "" },
{  "Rank" : "43", "Place" : "Mainland, China", "Continent" : "Asia", "Deaths to Cases - Last" : "0.0556" },
{  "Rank" : "", "Place" : "", "Continent" : "", "Deaths to Cases - Last" : "" },
{  "Rank" : "44", "Place" : "Switzerland", "Continent" : "Europe", "Deaths to Cases - Last" : "0.0538" },
{  "Rank" : "", "Place" : "", "Continent" : "", "Deaths to Cases - Last" : "" },
{  "Rank" : "45", "Place" : "Indonesia", "Continent" : "Asia", "Deaths to Cases - Last" : "0.0534" },
{  "Rank" : "", "Place" : "", "Continent" : "", "Deaths to Cases - Last" : "" },
{  "Rank" : "46", "Place" : "Japan", "Continent" : "Asia", "Deaths to Cases - Last" : "0.0532" },
{  "Rank" : "", "Place" : "", "Continent" : "", "Deaths to Cases - Last" : "" },
{  "Rank" : "47", "Place" : "United States of America", "Continent" : "North America", "Deaths to Cases - Last" : "0.0528" },
{  "Rank" : "", "Place" : "", "Continent" : "", "Deaths to Cases - Last" : "" },
{  "Rank" : "48", "Place" : "Liberia", "Continent" : "Africa", "Deaths to Cases - Last" : "0.0523" },
{  "Rank" : "", "Place" : "", "Continent" : "", "Deaths to Cases - Last" : "" },
{  "Rank" : "49", "Place" : "Bulgaria", "Continent" : "Europe", "Deaths to Cases - Last" : "0.052" },
{  "Rank" : "", "Place" : "", "Continent" : "", "Deaths to Cases - Last" : "" },
{  "Rank" : "50", "Place" : "Guernsey", "Continent" : "Europe", "Deaths to Cases - Last" : "0.0516" },
{  "Rank" : "", "Place" : "", "Continent" : "", "Deaths to Cases - Last" : "" },
{  "Rank" : "51", "Place" : "Angola", "Continent" : "Africa", "Deaths to Cases - Last" : "0.0492" },
{  "Rank" : "", "Place" : "", "Continent" : "", "Deaths to Cases - Last" : "" },
{  "Rank" : "52", "Place" : "Gambia", "Continent" : "Africa", "Deaths to Cases - Last" : "0.0488" },
{  "Rank" : "", "Place" : "", "Continent" : "", "Deaths to Cases - Last" : "" },
{  "Rank" : "53", "Place" : "Bosnia and Herzegovina", "Continent" : "Europe", "Deaths to Cases - Last" : "0.0482" },
{  "Rank" : "", "Place" : "", "Continent" : "", "Deaths to Cases - Last" : "" },
{  "Rank" : "54", "Place" : "Denmark", "Continent" : "Europe", "Deaths to Cases - Last" : "0.0481" },
{  "Rank" : "", "Place" : "", "Continent" : "", "Deaths to Cases - Last" : "" },
{  "Rank" : "55", "Place" : "North Macedonia", "Continent" : "Europe", "Deaths to Cases - Last" : "0.0475" },
{  "Rank" : "", "Place" : "", "Continent" : "", "Deaths to Cases - Last" : "" },
{  "Rank" : "56", "Place" : "Iran (Islamic Republic of)", "Continent" : "Asia", "Deaths to Cases - Last" : "0.0469" },
{  "Rank" : "", "Place" : "", "Continent" : "", "Deaths to Cases - Last" : "" },
{  "Rank" : "57", "Place" : "Brazil", "Continent" : "South America", "Deaths to Cases - Last" : "0.0466" },
{  "Rank" : "", "Place" : "", "Continent" : "", "Deaths to Cases - Last" : "" },
{  "Rank" : "57", "Place" : "Germany", "Continent" : "Europe", "Deaths to Cases - Last" : "0.0466" },
{  "Rank" : "", "Place" : "", "Continent" : "", "Deaths to Cases - Last" : "" },
{  "Rank" : "59", "Place" : "Finland", "Continent" : "Europe", "Deaths to Cases - Last" : "0.0458" },
{  "Rank" : "", "Place" : "", "Continent" : "", "Deaths to Cases - Last" : "" },
{  "Rank" : "59", "Place" : "Croatia", "Continent" : "Europe", "Deaths to Cases - Last" : "0.0458" },
{  "Rank" : "", "Place" : "", "Continent" : "", "Deaths to Cases - Last" : "" },
{  "Rank" : "61", "Place" : "Curacao", "Continent" : "South America", "Deaths to Cases - Last" : "0.0435" },
{  "Rank" : "", "Place" : "", "Continent" : "", "Deaths to Cases - Last" : "" },
{  "Rank" : "62", "Place" : "Tunisia", "Continent" : "Africa", "Deaths to Cases - Last" : "0.0431" },
{  "Rank" : "", "Place" : "", "Continent" : "", "Deaths to Cases - Last" : "" },
{  "Rank" : "63", "Place" : "Poland", "Continent" : "Europe", "Deaths to Cases - Last" : "0.0422" },
{  "Rank" : "", "Place" : "", "Continent" : "", "Deaths to Cases - Last" : "" },
{  "Rank" : "63", "Place" : "Lithuania", "Continent" : "Europe", "Deaths to Cases - Last" : "0.0422" },
{  "Rank" : "", "Place" : "", "Continent" : "", "Deaths to Cases - Last" : "" },
{  "Rank" : "65", "Place" : "United Republic of Tanzania", "Continent" : "Africa", "Deaths to Cases - Last" : "0.0413" },
{  "Rank" : "", "Place" : "", "Continent" : "", "Deaths to Cases - Last" : "" },
{  "Rank" : "66", "Place" : "Sierra Leone", "Continent" : "Africa", "Deaths to Cases - Last" : "0.041" },
{  "Rank" : "", "Place" : "", "Continent" : "", "Deaths to Cases - Last" : "" },
{  "Rank" : "67", "Place" : "Guatemala", "Continent" : "North America", "Deaths to Cases - Last" : "0.0404" },
{  "Rank" : "", "Place" : "", "Continent" : "", "Deaths to Cases - Last" : "" },
{  "Rank" : "68", "Place" : "Egypt", "Continent" : "Africa", "Deaths to Cases - Last" : "0.0401" },
{  "Rank" : "", "Place" : "", "Continent" : "", "Deaths to Cases - Last" : "" },
{  "Rank" : "69", "Place" : "Austria", "Continent" : "Europe", "Deaths to Cases - Last" : "0.0398" },
{  "Rank" : "", "Place" : "", "Continent" : "", "Deaths to Cases - Last" : "" },
{  "Rank" : "70", "Place" : "Portugal", "Continent" : "Europe", "Deaths to Cases - Last" : "0.0389" },
{  "Rank" : "", "Place" : "", "Continent" : "", "Deaths to Cases - Last" : "" },
{  "Rank" : "71", "Place" : "Philippines", "Continent" : "Asia", "Deaths to Cases - Last" : "0.0384" },
{  "Rank" : "", "Place" : "", "Continent" : "", "Deaths to Cases - Last" : "" },
{  "Rank" : "72", "Place" : "Mauritania", "Continent" : "Africa", "Deaths to Cases - Last" : "0.0372" },
{  "Rank" : "", "Place" : "", "Continent" : "", "Deaths to Cases - Last" : "" },
{  "Rank" : "73", "Place" : "Cuba", "Continent" : "North America", "Deaths to Cases - Last" : "0.0367" },
{  "Rank" : "", "Place" : "", "Continent" : "", "Deaths to Cases - Last" : "" },
{  "Rank" : "74", "Place" : "Iraq", "Continent" : "Asia", "Deaths to Cases - Last" : "0.0357" },
{  "Rank" : "", "Place" : "", "Continent" : "", "Deaths to Cases - Last" : "" },
{  "Rank" : "75", "Place" : "Estonia", "Continent" : "Europe", "Deaths to Cases - Last" : "0.0348" },
{  "Rank" : "", "Place" : "", "Continent" : "", "Deaths to Cases - Last" : "" },
{  "Rank" : "76", "Place" : "Congo", "Continent" : "Africa", "Deaths to Cases - Last" : "0.034" },
{  "Rank" : "", "Place" : "", "Continent" : "", "Deaths to Cases - Last" : "" },
{  "Rank" : "77", "Place" : "Republic of Moldova", "Continent" : "Europe", "Deaths to Cases - Last" : "0.0337" },
{  "Rank" : "", "Place" : "", "Continent" : "", "Deaths to Cases - Last" : "" },
{  "Rank" : "78", "Place" : "Colombia", "Continent" : "South America", "Deaths to Cases - Last" : "0.0326" },
{  "Rank" : "", "Place" : "", "Continent" : "", "Deaths to Cases - Last" : "" },
{  "Rank" : "79", "Place" : "Somalia", "Continent" : "Africa", "Deaths to Cases - Last" : "0.032" },
{  "Rank" : "", "Place" : "", "Continent" : "", "Deaths to Cases - Last" : "" },
{  "Rank" : "79", "Place" : "Syrian Arab Republic", "Continent" : "Asia", "Deaths to Cases - Last" : "0.032" },
{  "Rank" : "", "Place" : "", "Continent" : "", "Deaths to Cases - Last" : "" },
{  "Rank" : "81", "Place" : "Nicaragua", "Continent" : "North America", "Deaths to Cases - Last" : "0.0318" },
{  "Rank" : "", "Place" : "", "Continent" : "", "Deaths to Cases - Last" : "" },
{  "Rank" : "81", "Place" : "Czechia", "Continent" : "Europe", "Deaths to Cases - Last" : "0.0318" },
{  "Rank" : "", "Place" : "", "Continent" : "", "Deaths to Cases - Last" : "" },
{  "Rank" : "81", "Place" : "India", "Continent" : "Asia", "Deaths to Cases - Last" : "0.0318" },
{  "Rank" : "", "Place" : "", "Continent" : "", "Deaths to Cases - Last" : "" },
{  "Rank" : "84", "Place" : "Bolivia (Plurinational State of)", "Continent" : "South America", "Deaths to Cases - Last" : "0.0317" },
{  "Rank" : "", "Place" : "", "Continent" : "", "Deaths to Cases - Last" : "" },
{  "Rank" : "85", "Place" : "Peru", "Continent" : "South America", "Deaths to Cases - Last" : "0.0316" },
{  "Rank" : "", "Place" : "", "Continent" : "", "Deaths to Cases - Last" : "" },
{  "Rank" : "86", "Place" : "Aruba", "Continent" : "North America", "Deaths to Cases - Last" : "0.0297" },
{  "Rank" : "", "Place" : "", "Continent" : "", "Deaths to Cases - Last" : "" },
{  "Rank" : "87", "Place" : "Mauritius", "Continent" : "Africa", "Deaths to Cases - Last" : "0.0294" },
{  "Rank" : "", "Place" : "", "Continent" : "", "Deaths to Cases - Last" : "" },
{  "Rank" : "88", "Place" : "Uruguay", "Continent" : "South America", "Deaths to Cases - Last" : "0.0285" },
{  "Rank" : "", "Place" : "", "Continent" : "", "Deaths to Cases - Last" : "" },
{  "Rank" : "89", "Place" : "Norway", "Continent" : "Europe", "Deaths to Cases - Last" : "0.0284" },
{  "Rank" : "", "Place" : "", "Continent" : "", "Deaths to Cases - Last" : "" },
{  "Rank" : "90", "Place" : "Honduras", "Continent" : "North America", "Deaths to Cases - Last" : "0.0283" },
{  "Rank" : "", "Place" : "", "Continent" : "", "Deaths to Cases - Last" : "" },
{  "Rank" : "91", "Place" : "Ukraine", "Continent" : "Europe", "Deaths to Cases - Last" : "0.0272" },
{  "Rank" : "", "Place" : "", "Continent" : "", "Deaths to Cases - Last" : "" },
{  "Rank" : "92", "Place" : "Latvia", "Continent" : "Europe", "Deaths to Cases - Last" : "0.027" },
{  "Rank" : "", "Place" : "", "Continent" : "", "Deaths to Cases - Last" : "" },
{  "Rank" : "93", "Place" : "Luxembourg", "Continent" : "Europe", "Deaths to Cases - Last" : "0.0267" },
{  "Rank" : "", "Place" : "", "Continent" : "", "Deaths to Cases - Last" : "" },
{  "Rank" : "94", "Place" : "Turkey", "Continent" : "Europe", "Deaths to Cases - Last" : "0.0263" },
{  "Rank" : "", "Place" : "", "Continent" : "", "Deaths to Cases - Last" : "" },
{  "Rank" : "95", "Place" : "Kenya", "Continent" : "Africa", "Deaths to Cases - Last" : "0.0261" },
{  "Rank" : "", "Place" : "", "Continent" : "", "Deaths to Cases - Last" : "" },
{  "Rank" : "96", "Place" : "Sao Tome and Principe", "Continent" : "Africa", "Deaths to Cases - Last" : "0.0258" },
{  "Rank" : "", "Place" : "", "Continent" : "", "Deaths to Cases - Last" : "" },
{  "Rank" : "97", "Place" : "Cameroon", "Continent" : "Africa", "Deaths to Cases - Last" : "0.0255" },
{  "Rank" : "", "Place" : "", "Continent" : "", "Deaths to Cases - Last" : "" },
{  "Rank" : "98", "Place" : "Suriname", "Continent" : "South America", "Deaths to Cases - Last" : "0.0252" },
{  "Rank" : "", "Place" : "", "Continent" : "", "Deaths to Cases - Last" : "" },
{  "Rank" : "99", "Place" : "Nigeria", "Continent" : "Africa", "Deaths to Cases - Last" : "0.0251" },
{  "Rank" : "", "Place" : "", "Continent" : "", "Deaths to Cases - Last" : "" },
{  "Rank" : "100", "Place" : "Dominican Republic", "Continent" : "North America", "Deaths to Cases - Last" : "0.0244" },
{  "Rank" : "", "Place" : "", "Continent" : "", "Deaths to Cases - Last" : "" },
{  "Rank" : "101", "Place" : "Montenegro", "Continent" : "Europe", "Deaths to Cases - Last" : "0.024" },
{  "Rank" : "", "Place" : "", "Continent" : "", "Deaths to Cases - Last" : "" },
{  "Rank" : "102", "Place" : "Argentina", "Continent" : "South America", "Deaths to Cases - Last" : "0.0237" },
{  "Rank" : "", "Place" : "", "Continent" : "", "Deaths to Cases - Last" : "" },
{  "Rank" : "103", "Place" : "Guam", "Continent" : "Oceania", "Deaths to Cases - Last" : "0.0231" },
{  "Rank" : "", "Place" : "", "Continent" : "", "Deaths to Cases - Last" : "" },
{  "Rank" : "104", "Place" : "Togo", "Continent" : "Africa", "Deaths to Cases - Last" : "0.0228" },
{  "Rank" : "", "Place" : "", "Continent" : "", "Deaths to Cases - Last" : "" },
{  "Rank" : "105", "Place" : "Puerto Rico", "Continent" : "North America", "Deaths to Cases - Last" : "0.0227" },
{  "Rank" : "", "Place" : "", "Continent" : "", "Deaths to Cases - Last" : "" },
{  "Rank" : "106", "Place" : "Democratic Republic of the Congo", "Continent" : "Africa", "Deaths to Cases - Last" : "0.0226" },
{  "Rank" : "", "Place" : "", "Continent" : "", "Deaths to Cases - Last" : "" },
{  "Rank" : "107", "Place" : "Republic of Korea", "Continent" : "Asia", "Deaths to Cases - Last" : "0.0225" },
{  "Rank" : "", "Place" : "", "Continent" : "", "Deaths to Cases - Last" : "" },
{  "Rank" : "108", "Place" : "El Salvador", "Continent" : "North America", "Deaths to Cases - Last" : "0.0223" },
{  "Rank" : "", "Place" : "", "Continent" : "", "Deaths to Cases - Last" : "" },
{  "Rank" : "109", "Place" : "Albania", "Continent" : "Europe", "Deaths to Cases - Last" : "0.022" },
{  "Rank" : "", "Place" : "", "Continent" : "", "Deaths to Cases - Last" : "" },
{  "Rank" : "110", "Place" : "Brunei Darussalam", "Continent" : "Asia", "Deaths to Cases - Last" : "0.0213" },
{  "Rank" : "", "Place" : "", "Continent" : "", "Deaths to Cases - Last" : "" },
{  "Rank" : "111", "Place" : "Afghanistan", "Continent" : "Asia", "Deaths to Cases - Last" : "0.021" },
{  "Rank" : "", "Place" : "", "Continent" : "", "Deaths to Cases - Last" : "" },
{  "Rank" : "111", "Place" : "Morocco", "Continent" : "Africa", "Deaths to Cases - Last" : "0.021" },
{  "Rank" : "", "Place" : "", "Continent" : "", "Deaths to Cases - Last" : "" },
{  "Rank" : "113", "Place" : "Myanmar", "Continent" : "Asia", "Deaths to Cases - Last" : "0.0206" },
{  "Rank" : "", "Place" : "", "Continent" : "", "Deaths to Cases - Last" : "" },
{  "Rank" : "114", "Place" : "Comoros", "Continent" : "Africa", "Deaths to Cases - Last" : "0.0202" },
{  "Rank" : "", "Place" : "", "Continent" : "", "Deaths to Cases - Last" : "" },
{  "Rank" : "114", "Place" : "Serbia", "Continent" : "Europe", "Deaths to Cases - Last" : "0.0202" },
{  "Rank" : "", "Place" : "", "Continent" : "", "Deaths to Cases - Last" : "" },
{  "Rank" : "116", "Place" : "Pakistan", "Continent" : "Asia", "Deaths to Cases - Last" : "0.02" },
{  "Rank" : "", "Place" : "", "Continent" : "", "Deaths to Cases - Last" : "" },
{  "Rank" : "116", "Place" : "Lebanon", "Continent" : "Asia", "Deaths to Cases - Last" : "0.02" },
{  "Rank" : "", "Place" : "", "Continent" : "", "Deaths to Cases - Last" : "" },
{  "Rank" : "118", "Place" : "South Africa", "Continent" : "Africa", "Deaths to Cases - Last" : "0.0196" },
{  "Rank" : "", "Place" : "", "Continent" : "", "Deaths to Cases - Last" : "" },
{  "Rank" : "119", "Place" : "Panama", "Continent" : "North America", "Deaths to Cases - Last" : "0.0192" },
{  "Rank" : "", "Place" : "", "Continent" : "", "Deaths to Cases - Last" : "" },
{  "Rank" : "119", "Place" : "Cyprus", "Continent" : "Europe", "Deaths to Cases - Last" : "0.0192" },
{  "Rank" : "", "Place" : "", "Continent" : "", "Deaths to Cases - Last" : "" },
{  "Rank" : "121", "Place" : "New Zealand", "Continent" : "Oceania", "Deaths to Cases - Last" : "0.0189" },
{  "Rank" : "", "Place" : "", "Continent" : "", "Deaths to Cases - Last" : "" },
{  "Rank" : "122", "Place" : "Thailand", "Continent" : "Asia", "Deaths to Cases - Last" : "0.0184" },
{  "Rank" : "", "Place" : "", "Continent" : "", "Deaths to Cases - Last" : "" },
{  "Rank" : "123", "Place" : "Chile", "Continent" : "South America", "Deaths to Cases - Last" : "0.0182" },
{  "Rank" : "", "Place" : "", "Continent" : "", "Deaths to Cases - Last" : "" },
{  "Rank" : "124", "Place" : "South Sudan", "Continent" : "Africa", "Deaths to Cases - Last" : "0.018" },
{  "Rank" : "", "Place" : "", "Continent" : "", "Deaths to Cases - Last" : "" },
{  "Rank" : "125", "Place" : "Armenia", "Continent" : "Europe", "Deaths to Cases - Last" : "0.0177" },
{  "Rank" : "", "Place" : "", "Continent" : "", "Deaths to Cases - Last" : "" },
{  "Rank" : "126", "Place" : "Slovakia", "Continent" : "Europe", "Deaths to Cases - Last" : "0.0176" },
{  "Rank" : "", "Place" : "", "Continent" : "", "Deaths to Cases - Last" : "" },
{  "Rank" : "127", "Place" : "Libya", "Continent" : "Africa", "Deaths to Cases - Last" : "0.0175" },
{  "Rank" : "", "Place" : "", "Continent" : "", "Deaths to Cases - Last" : "" },
{  "Rank" : "127", "Place" : "International conveyance", "Continent" : "", "Deaths to Cases - Last" : "0.0175" },
{  "Rank" : "", "Place" : "", "Continent" : "", "Deaths to Cases - Last" : "" },
{  "Rank" : "129", "Place" : "Haiti", "Continent" : "North America", "Deaths to Cases - Last" : "0.0169" },
{  "Rank" : "", "Place" : "", "Continent" : "", "Deaths to Cases - Last" : "" },
{  "Rank" : "130", "Place" : "Ethiopia", "Continent" : "Africa", "Deaths to Cases - Last" : "0.0161" },
{  "Rank" : "", "Place" : "", "Continent" : "", "Deaths to Cases - Last" : "" },
{  "Rank" : "130", "Place" : "Benin", "Continent" : "Africa", "Deaths to Cases - Last" : "0.0161" },
{  "Rank" : "", "Place" : "", "Continent" : "", "Deaths to Cases - Last" : "" },
{  "Rank" : "132", "Place" : "Taiwan, China", "Continent" : "Asia", "Deaths to Cases - Last" : "0.0157" },
{  "Rank" : "", "Place" : "", "Continent" : "", "Deaths to Cases - Last" : "" },
{  "Rank" : "133", "Place" : "Georgia", "Continent" : "Europe", "Deaths to Cases - Last" : "0.0154" },
{  "Rank" : "", "Place" : "", "Continent" : "", "Deaths to Cases - Last" : "" },
{  "Rank" : "134", "Place" : "Jamaica", "Continent" : "North America", "Deaths to Cases - Last" : "0.0152" },
{  "Rank" : "", "Place" : "", "Continent" : "", "Deaths to Cases - Last" : "" },
{  "Rank" : "135", "Place" : "Malawi", "Continent" : "Africa", "Deaths to Cases - Last" : "0.0148" },
{  "Rank" : "", "Place" : "", "Continent" : "", "Deaths to Cases - Last" : "" },
{  "Rank" : "136", "Place" : "Israel", "Continent" : "Asia", "Deaths to Cases - Last" : "0.0147" },
{  "Rank" : "", "Place" : "", "Continent" : "", "Deaths to Cases - Last" : "" },
{  "Rank" : "137", "Place" : "Senegal", "Continent" : "Africa", "Deaths to Cases - Last" : "0.0144" },
{  "Rank" : "", "Place" : "", "Continent" : "", "Deaths to Cases - Last" : "" },
{  "Rank" : "138", "Place" : "Malaysia", "Continent" : "Asia", "Deaths to Cases - Last" : "0.0141" },
{  "Rank" : "", "Place" : "", "Continent" : "", "Deaths to Cases - Last" : "" },
{  "Rank" : "139", "Place" : "Russian Federation", "Continent" : "Europe", "Deaths to Cases - Last" : "0.0139" },
{  "Rank" : "", "Place" : "", "Continent" : "", "Deaths to Cases - Last" : "" },
{  "Rank" : "140", "Place" : "Australia", "Continent" : "Oceania", "Deaths to Cases - Last" : "0.0136" },
{  "Rank" : "", "Place" : "", "Continent" : "", "Deaths to Cases - Last" : "" },
{  "Rank" : "141", "Place" : "Malta", "Continent" : "Europe", "Deaths to Cases - Last" : "0.0135" },
{  "Rank" : "", "Place" : "", "Continent" : "", "Deaths to Cases - Last" : "" },
{  "Rank" : "142", "Place" : "Mayotte", "Continent" : "Africa", "Deaths to Cases - Last" : "0.0131" },
{  "Rank" : "", "Place" : "", "Continent" : "", "Deaths to Cases - Last" : "" },
{  "Rank" : "143", "Place" : "Bangladesh", "Continent" : "Asia", "Deaths to Cases - Last" : "0.013" },
{  "Rank" : "", "Place" : "", "Continent" : "", "Deaths to Cases - Last" : "" },
{  "Rank" : "144", "Place" : "Kosovo", "Continent" : "Europe", "Deaths to Cases - Last" : "0.0124" },
{  "Rank" : "", "Place" : "", "Continent" : "", "Deaths to Cases - Last" : "" },
{  "Rank" : "145", "Place" : "Guinea-Bissau", "Continent" : "Africa", "Deaths to Cases - Last" : "0.0122" },
{  "Rank" : "", "Place" : "", "Continent" : "", "Deaths to Cases - Last" : "" },
{  "Rank" : "145", "Place" : "Azerbaijan", "Continent" : "Europe", "Deaths to Cases - Last" : "0.0122" },
{  "Rank" : "", "Place" : "", "Continent" : "", "Deaths to Cases - Last" : "" },
{  "Rank" : "147", "Place" : "Liechtenstein", "Continent" : "Europe", "Deaths to Cases - Last" : "0.012" },
{  "Rank" : "", "Place" : "", "Continent" : "", "Deaths to Cases - Last" : "" },
{  "Rank" : "148", "Place" : "Zimbabwe", "Continent" : "Africa", "Deaths to Cases - Last" : "0.0117" },
{  "Rank" : "", "Place" : "", "Continent" : "", "Deaths to Cases - Last" : "" },
{  "Rank" : "148", "Place" : "Kyrgyzstan", "Continent" : "Asia", "Deaths to Cases - Last" : "0.0117" },
{  "Rank" : "", "Place" : "", "Continent" : "", "Deaths to Cases - Last" : "" },
{  "Rank" : "150", "Place" : "Equatorial Guinea", "Continent" : "Africa", "Deaths to Cases - Last" : "0.0115" },
{  "Rank" : "", "Place" : "", "Continent" : "", "Deaths to Cases - Last" : "" },
{  "Rank" : "151", "Place" : "Botswana", "Continent" : "Africa", "Deaths to Cases - Last" : "0.0112" },
{  "Rank" : "", "Place" : "", "Continent" : "", "Deaths to Cases - Last" : "" },
{  "Rank" : "152", "Place" : "Djibouti", "Continent" : "Africa", "Deaths to Cases - Last" : "0.0104" },
{  "Rank" : "", "Place" : "", "Continent" : "", "Deaths to Cases - Last" : "" },
{  "Rank" : "153", "Place" : "Central African Republic", "Continent" : "Africa", "Deaths to Cases - Last" : "0.0101" },
{  "Rank" : "", "Place" : "", "Continent" : "", "Deaths to Cases - Last" : "" },
{  "Rank" : "153", "Place" : "Monaco", "Continent" : "Europe", "Deaths to Cases - Last" : "0.0101" },
{  "Rank" : "", "Place" : "", "Continent" : "", "Deaths to Cases - Last" : "" },
{  "Rank" : "155", "Place" : "Tajikistan", "Continent" : "Asia", "Deaths to Cases - Last" : "0.0094" },
{  "Rank" : "", "Place" : "", "Continent" : "", "Deaths to Cases - Last" : "" },
{  "Rank" : "156", "Place" : "Eswatini", "Continent" : "Africa", "Deaths to Cases - Last" : "0.0093" },
{  "Rank" : "", "Place" : "", "Continent" : "", "Deaths to Cases - Last" : "" },
{  "Rank" : "156", "Place" : "Paraguay", "Continent" : "South America", "Deaths to Cases - Last" : "0.0093" },
{  "Rank" : "", "Place" : "", "Continent" : "", "Deaths to Cases - Last" : "" },
{  "Rank" : "158", "Place" : "Madagascar", "Continent" : "Africa", "Deaths to Cases - Last" : "0.0091" },
{  "Rank" : "", "Place" : "", "Continent" : "", "Deaths to Cases - Last" : "" },
{  "Rank" : "159", "Place" : "Jordan", "Continent" : "Asia", "Deaths to Cases - Last" : "0.0086" },
{  "Rank" : "", "Place" : "", "Continent" : "", "Deaths to Cases - Last" : "" },
{  "Rank" : "160", "Place" : "Cabo Verde", "Continent" : "Africa", "Deaths to Cases - Last" : "0.0085" },
{  "Rank" : "", "Place" : "", "Continent" : "", "Deaths to Cases - Last" : "" },
{  "Rank" : "161", "Place" : "Venezuela (Bolivarian Republic of)", "Continent" : "South America", "Deaths to Cases - Last" : "0.0084" },
{  "Rank" : "", "Place" : "", "Continent" : "", "Deaths to Cases - Last" : "" },
{  "Rank" : "162", "Place" : "Gabon", "Continent" : "Africa", "Deaths to Cases - Last" : "0.0082" },
{  "Rank" : "", "Place" : "", "Continent" : "", "Deaths to Cases - Last" : "" },
{  "Rank" : "162", "Place" : "Kuwait", "Continent" : "Asia", "Deaths to Cases - Last" : "0.0082" },
{  "Rank" : "", "Place" : "", "Continent" : "", "Deaths to Cases - Last" : "" },
{  "Rank" : "164", "Place" : "Saudi Arabia", "Continent" : "Asia", "Deaths to Cases - Last" : "0.0081" },
{  "Rank" : "", "Place" : "", "Continent" : "", "Deaths to Cases - Last" : "" },
{  "Rank" : "165", "Place" : "Zambia", "Continent" : "Africa", "Deaths to Cases - Last" : "0.0077" },
{  "Rank" : "", "Place" : "", "Continent" : "", "Deaths to Cases - Last" : "" },
{  "Rank" : "166", "Place" : "Cote d Ivoire", "Continent" : "Africa", "Deaths to Cases - Last" : "0.0073" },
{  "Rank" : "", "Place" : "", "Continent" : "", "Deaths to Cases - Last" : "" },
{  "Rank" : "167", "Place" : "Kazakhstan", "Continent" : "Europe", "Deaths to Cases - Last" : "0.007" },
{  "Rank" : "", "Place" : "", "Continent" : "", "Deaths to Cases - Last" : "" },
{  "Rank" : "168", "Place" : "Burundi", "Continent" : "Africa", "Deaths to Cases - Last" : "0.0069" },
{  "Rank" : "", "Place" : "", "Continent" : "", "Deaths to Cases - Last" : "" },
{  "Rank" : "169", "Place" : "Mozambique", "Continent" : "Africa", "Deaths to Cases - Last" : "0.0068" },
{  "Rank" : "", "Place" : "", "Continent" : "", "Deaths to Cases - Last" : "" },
{  "Rank" : "170", "Place" : "United Arab Emirates", "Continent" : "Asia", "Deaths to Cases - Last" : "0.0067" },
{  "Rank" : "", "Place" : "", "Continent" : "", "Deaths to Cases - Last" : "" },
{  "Rank" : "171", "Place" : "Ghana", "Continent" : "Africa", "Deaths to Cases - Last" : "0.006" },
{  "Rank" : "", "Place" : "", "Continent" : "", "Deaths to Cases - Last" : "" },
{  "Rank" : "172", "Place" : "Belarus", "Continent" : "Europe", "Deaths to Cases - Last" : "0.0059" },
{  "Rank" : "", "Place" : "", "Continent" : "", "Deaths to Cases - Last" : "" },
{  "Rank" : "173", "Place" : "Sri Lanka", "Continent" : "Asia", "Deaths to Cases - Last" : "0.0056" },
{  "Rank" : "", "Place" : "", "Continent" : "", "Deaths to Cases - Last" : "" },
{  "Rank" : "174", "Place" : "Iceland", "Continent" : "Europe", "Deaths to Cases - Last" : "0.0055" },
{  "Rank" : "", "Place" : "", "Continent" : "", "Deaths to Cases - Last" : "" },
{  "Rank" : "175", "Place" : "Guinea", "Continent" : "Africa", "Deaths to Cases - Last" : "0.0054" },
{  "Rank" : "", "Place" : "", "Continent" : "", "Deaths to Cases - Last" : "" },
{  "Rank" : "175", "Place" : "Costa Rica", "Continent" : "North America", "Deaths to Cases - Last" : "0.0054" },
{  "Rank" : "", "Place" : "", "Continent" : "", "Deaths to Cases - Last" : "" },
{  "Rank" : "177", "Place" : "Cayman Islands", "Continent" : "North America", "Deaths to Cases - Last" : "0.0051" },
{  "Rank" : "", "Place" : "", "Continent" : "", "Deaths to Cases - Last" : "" },
{  "Rank" : "178", "Place" : "Oman", "Continent" : "Asia", "Deaths to Cases - Last" : "0.0044" },
{  "Rank" : "", "Place" : "", "Continent" : "", "Deaths to Cases - Last" : "" },
{  "Rank" : "179", "Place" : "Hong Kong, China", "Continent" : "Asia", "Deaths to Cases - Last" : "0.0042" },
{  "Rank" : "", "Place" : "", "Continent" : "", "Deaths to Cases - Last" : "" },
{  "Rank" : "179", "Place" : "occupied Palestinian territory", "Continent" : "Asia", "Deaths to Cases - Last" : "0.0042" },
{  "Rank" : "", "Place" : "", "Continent" : "", "Deaths to Cases - Last" : "" },
{  "Rank" : "181", "Place" : "Maldives", "Continent" : "Asia", "Deaths to Cases - Last" : "0.0036" },
{  "Rank" : "", "Place" : "", "Continent" : "", "Deaths to Cases - Last" : "" },
{  "Rank" : "182", "Place" : "French Guiana", "Continent" : "South America", "Deaths to Cases - Last" : "0.0033" },
{  "Rank" : "", "Place" : "", "Continent" : "", "Deaths to Cases - Last" : "" },
{  "Rank" : "183", "Place" : "Bahrain", "Continent" : "Asia", "Deaths to Cases - Last" : "0.0029" },
{  "Rank" : "", "Place" : "", "Continent" : "", "Deaths to Cases - Last" : "" },
{  "Rank" : "183", "Place" : "Uzbekistan", "Continent" : "Asia", "Deaths to Cases - Last" : "0.0029" },
{  "Rank" : "", "Place" : "", "Continent" : "", "Deaths to Cases - Last" : "" },
{  "Rank" : "185", "Place" : "Rwanda", "Continent" : "Africa", "Deaths to Cases - Last" : "0.0025" },
{  "Rank" : "", "Place" : "", "Continent" : "", "Deaths to Cases - Last" : "" },
{  "Rank" : "186", "Place" : "Nepal", "Continent" : "Asia", "Deaths to Cases - Last" : "0.0024" },
{  "Rank" : "", "Place" : "", "Continent" : "", "Deaths to Cases - Last" : "" },
{  "Rank" : "187", "Place" : "Reunion", "Continent" : "Africa", "Deaths to Cases - Last" : "0.002" },
{  "Rank" : "", "Place" : "", "Continent" : "", "Deaths to Cases - Last" : "" },
{  "Rank" : "188", "Place" : "Qatar", "Continent" : "Asia", "Deaths to Cases - Last" : "0.0011" },
{  "Rank" : "", "Place" : "", "Continent" : "", "Deaths to Cases - Last" : "" },
{  "Rank" : "189", "Place" : "Singapore", "Continent" : "Asia", "Deaths to Cases - Last" : "0.0006" },
{  "Rank" : "", "Place" : "", "Continent" : "", "Deaths to Cases - Last" : "" },
{  "Rank" : "190", "Place" : "Macau, China", "Continent" : "Asia", "Deaths to Cases - Last" : "0" },
{  "Rank" : "", "Place" : "", "Continent" : "", "Deaths to Cases - Last" : "" },
{  "Rank" : "190", "Place" : "Uganda", "Continent" : "Africa", "Deaths to Cases - Last" : "0" },
{  "Rank" : "", "Place" : "", "Continent" : "", "Deaths to Cases - Last" : "" },
{  "Rank" : "190", "Place" : "Eritrea", "Continent" : "Africa", "Deaths to Cases - Last" : "0" },
{  "Rank" : "", "Place" : "", "Continent" : "", "Deaths to Cases - Last" : "" },
{  "Rank" : "190", "Place" : "Namibia", "Continent" : "Africa", "Deaths to Cases - Last" : "0" },
{  "Rank" : "", "Place" : "", "Continent" : "", "Deaths to Cases - Last" : "" },
{  "Rank" : "190", "Place" : "Lesotho", "Continent" : "Africa", "Deaths to Cases - Last" : "0" },
{  "Rank" : "", "Place" : "", "Continent" : "", "Deaths to Cases - Last" : "" },
{  "Rank" : "190", "Place" : "Seychelles", "Continent" : "Africa", "Deaths to Cases - Last" : "0" },
{  "Rank" : "", "Place" : "", "Continent" : "", "Deaths to Cases - Last" : "" },
{  "Rank" : "190", "Place" : "Saint Vincent and the Grenadines", "Continent" : "North America", "Deaths to Cases - Last" : "0" },
{  "Rank" : "", "Place" : "", "Continent" : "", "Deaths to Cases - Last" : "" },
{  "Rank" : "190", "Place" : "Grenada", "Continent" : "North America", "Deaths to Cases - Last" : "0" },
{  "Rank" : "", "Place" : "", "Continent" : "", "Deaths to Cases - Last" : "" },
{  "Rank" : "190", "Place" : "Saint Lucia", "Continent" : "North America", "Deaths to Cases - Last" : "0" },
{  "Rank" : "", "Place" : "", "Continent" : "", "Deaths to Cases - Last" : "" },
{  "Rank" : "190", "Place" : "Dominica", "Continent" : "North America", "Deaths to Cases - Last" : "0" },
{  "Rank" : "", "Place" : "", "Continent" : "", "Deaths to Cases - Last" : "" },
{  "Rank" : "190", "Place" : "Saint Kitts and Nevis", "Continent" : "North America", "Deaths to Cases - Last" : "0" },
{  "Rank" : "", "Place" : "", "Continent" : "", "Deaths to Cases - Last" : "" },
{  "Rank" : "190", "Place" : "Falkland Islands (Malvinas)", "Continent" : "South America", "Deaths to Cases - Last" : "0" },
{  "Rank" : "", "Place" : "", "Continent" : "", "Deaths to Cases - Last" : "" },
{  "Rank" : "190", "Place" : "Bonaire, Sint Eustatius and Saba", "Continent" : "South America", "Deaths to Cases - Last" : "0" },
{  "Rank" : "", "Place" : "", "Continent" : "", "Deaths to Cases - Last" : "" },
{  "Rank" : "190", "Place" : "Saint Barthelemy", "Continent" : "North America", "Deaths to Cases - Last" : "0" },
{  "Rank" : "", "Place" : "", "Continent" : "", "Deaths to Cases - Last" : "" },
{  "Rank" : "190", "Place" : "Anguilla", "Continent" : "North America", "Deaths to Cases - Last" : "0" },
{  "Rank" : "", "Place" : "", "Continent" : "", "Deaths to Cases - Last" : "" },
{  "Rank" : "190", "Place" : "Saint Pierre and Miquelon", "Continent" : "North America", "Deaths to Cases - Last" : "0" },
{  "Rank" : "", "Place" : "", "Continent" : "", "Deaths to Cases - Last" : "" },
{  "Rank" : "190", "Place" : "Holy See", "Continent" : "Europe", "Deaths to Cases - Last" : "0" },
{  "Rank" : "", "Place" : "", "Continent" : "", "Deaths to Cases - Last" : "" },
{  "Rank" : "190", "Place" : "Faroe Islands", "Continent" : "Europe", "Deaths to Cases - Last" : "0" },
{  "Rank" : "", "Place" : "", "Continent" : "", "Deaths to Cases - Last" : "" },
{  "Rank" : "190", "Place" : "Gibraltar", "Continent" : "Europe", "Deaths to Cases - Last" : "0" },
{  "Rank" : "", "Place" : "", "Continent" : "", "Deaths to Cases - Last" : "" },
{  "Rank" : "190", "Place" : "Greenland", "Continent" : "North America", "Deaths to Cases - Last" : "0" },
{  "Rank" : "", "Place" : "", "Continent" : "", "Deaths to Cases - Last" : "" },
{  "Rank" : "190", "Place" : "Bhutan", "Continent" : "Asia", "Deaths to Cases - Last" : "0" },
{  "Rank" : "", "Place" : "", "Continent" : "", "Deaths to Cases - Last" : "" },
{  "Rank" : "190", "Place" : "Timor-Leste", "Continent" : "Asia", "Deaths to Cases - Last" : "0" },
{  "Rank" : "", "Place" : "", "Continent" : "", "Deaths to Cases - Last" : "" },
{  "Rank" : "190", "Place" : "Viet Nam", "Continent" : "Asia", "Deaths to Cases - Last" : "0" },
{  "Rank" : "", "Place" : "", "Continent" : "", "Deaths to Cases - Last" : "" },
{  "Rank" : "190", "Place" : "Mongolia", "Continent" : "Asia", "Deaths to Cases - Last" : "0" },
{  "Rank" : "", "Place" : "", "Continent" : "", "Deaths to Cases - Last" : "" },
{  "Rank" : "190", "Place" : "Cambodia", "Continent" : "Asia", "Deaths to Cases - Last" : "0" },
{  "Rank" : "", "Place" : "", "Continent" : "", "Deaths to Cases - Last" : "" },
{  "Rank" : "190", "Place" : "Lao People's Democratic Republic", "Continent" : "Asia", "Deaths to Cases - Last" : "0" },
{  "Rank" : "", "Place" : "", "Continent" : "", "Deaths to Cases - Last" : "" },
{  "Rank" : "190", "Place" : "Fiji", "Continent" : "Oceania", "Deaths to Cases - Last" : "0" },
{  "Rank" : "", "Place" : "", "Continent" : "", "Deaths to Cases - Last" : "" },
{  "Rank" : "190", "Place" : "Papua New Guinea", "Continent" : "Oceania", "Deaths to Cases - Last" : "0" },
{  "Rank" : "", "Place" : "", "Continent" : "", "Deaths to Cases - Last" : "" },
{  "Rank" : "190", "Place" : "French Polynesia", "Continent" : "Oceania", "Deaths to Cases - Last" : "0" },
{  "Rank" : "", "Place" : "", "Continent" : "", "Deaths to Cases - Last" : "" },
{  "Rank" : "190", "Place" : "New Caledonia", "Continent" : "Oceania", "Deaths to Cases - Last" : "0" }
]
